<?xml version="1.0" encoding="UTF-8"?>
<java version="11.0.5" class="java.beans.XMLDecoder">
 <object class="java.util.HashMap">
  <void method="put">
   <string>1</string>
   <object class="entity.Grade">
    <void property="date">
     <object class="java.time.LocalDateTime" method="of">
      <int>2019</int>
      <object class="java.lang.Enum" method="valueOf">
       <class>java.time.Month</class>
       <string>DECEMBER</string>
      </object>
      <int>8</int>
      <int>20</int>
      <int>24</int>
      <int>51</int>
     </object>
    </void>
    <void property="feedback">
     <string>feedback</string>
    </void>
    <void property="grade">
     <int>9</int>
    </void>
    <void property="homeworkId">
     <string>1</string>
    </void>
    <void property="id">
     <string>1</string>
    </void>
    <void property="professor">
     <string>gigi</string>
    </void>
    <void property="studentId">
     <string>1</string>
    </void>
   </object>
  </void>
 </object>
</java>
